README.rst
setup.py
django_tabula_auth.egg-info/PKG-INFO
django_tabula_auth.egg-info/SOURCES.txt
django_tabula_auth.egg-info/dependency_links.txt
django_tabula_auth.egg-info/requires.txt
django_tabula_auth.egg-info/top_level.txt
tabula_auth/__init__.py
tabula_auth/admin.py
tabula_auth/apps.py
tabula_auth/exceptions.py
tabula_auth/models.py
tabula_auth/urls.py
tabula_auth/backends/__init__.py
tabula_auth/backends/phone_backend.py
tabula_auth/migrations/0001_initial.py
tabula_auth/migrations/0002_auto_20180608_1954.py
tabula_auth/migrations/__init__.py
tabula_auth/serializers/__init__.py
tabula_auth/serializers/otp_serializer.py
tabula_auth/serializers/user_serializer.py
tabula_auth/utils/__init__.py
tabula_auth/utils/sms_backend.py
tabula_auth/utils/sms_sending.py
tabula_auth/views/__init__.py
tabula_auth/views/otp_views.py
tabula_auth/views/user_views.py